multitasking/__init__.py
python_multitasking-0.0.9.dist-info/LICENSE.txt
python_multitasking-0.0.9.dist-info/METADATA
python_multitasking-0.0.9.dist-info/WHEEL
python_multitasking-0.0.9.dist-info/top_level.txt
python_multitasking-0.0.9.dist-info/RECORD
