Metadata-Version: 2.1
Name: python-multitasking
Version: 0.0.9
Summary: Non-blocking Python methods using decorators
Home-page: https://github.com/ranaroussi/multitasking
Author: Ran Aroussi
Author-email: ran@aroussi.com
License: Apache
Keywords: multitasking multitask threading async
Platform: any
Classifier: License :: OSI Approved :: Apache Software License
Classifier: Development Status :: 5 - Production/Stable
Classifier: Operating System :: OS Independent
Classifier: Intended Audience :: Developers
Classifier: Topic :: Software Development :: Libraries
Classifier: Topic :: Software Development :: Libraries :: Python Modules
Classifier: Programming Language :: Python :: 2.7
Classifier: Programming Language :: Python :: 3.5
Classifier: Programming Language :: Python :: 3.6
Classifier: Programming Language :: Python :: 3.7
